open_source_theme
