Metadata-Version: 2.1
Name: mkdocs-opensource
Version: 0.0.1
Summary: oceanbase static site theme
Home-page: UNKNOWN
Author: zhouzi
Author-email: 3222676446@qq.com
License: UNKNOWN
Platform: UNKNOWN
